ml_caboodle/__init__.py
ml_caboodle/feature_selection/__init__.py
ml_caboodle/feature_selection/recursive_select_from_model.py
ml_caboodle/feature_selection/wrapper_feature_selection.py
ml_caboodle-0.2.2.dist-info/WHEEL
ml_caboodle-0.2.2.dist-info/METADATA
ml_caboodle-0.2.2.dist-info/RECORD
